{
	"cmake" : 
	{
		"generator" : 
		{
			"multiConfig" : false,
			"name" : "Ninja"
		},
		"paths" : 
		{
			"cmake" : "/home/itsatompc/Qt/Tools/CMake/bin/cmake",
			"cpack" : "/home/itsatompc/Qt/Tools/CMake/bin/cpack",
			"ctest" : "/home/itsatompc/Qt/Tools/CMake/bin/ctest",
			"root" : "/home/itsatompc/Qt/Tools/CMake/share/cmake-3.30"
		},
		"version" : 
		{
			"isDirty" : false,
			"major" : 3,
			"minor" : 30,
			"patch" : 5,
			"string" : "3.30.5",
			"suffix" : ""
		}
	},
	"objects" : 
	[
		{
			"jsonFile" : "codemodel-v2-05aebf1ed0cf048e9863.json",
			"kind" : "codemodel",
			"version" : 
			{
				"major" : 2,
				"minor" : 7
			}
		},
		{
			"jsonFile" : "cache-v2-8441f0467c7c29dbe8a0.json",
			"kind" : "cache",
			"version" : 
			{
				"major" : 2,
				"minor" : 0
			}
		},
		{
			"jsonFile" : "cmakeFiles-v1-7ea8f94fdca9abe0f3db.json",
			"kind" : "cmakeFiles",
			"version" : 
			{
				"major" : 1,
				"minor" : 1
			}
		}
	],
	"reply" : 
	{
		"cache-v2" : 
		{
			"jsonFile" : "cache-v2-8441f0467c7c29dbe8a0.json",
			"kind" : "cache",
			"version" : 
			{
				"major" : 2,
				"minor" : 0
			}
		},
		"cmakeFiles-v1" : 
		{
			"jsonFile" : "cmakeFiles-v1-7ea8f94fdca9abe0f3db.json",
			"kind" : "cmakeFiles",
			"version" : 
			{
				"major" : 1,
				"minor" : 1
			}
		},
		"codemodel-v2" : 
		{
			"jsonFile" : "codemodel-v2-05aebf1ed0cf048e9863.json",
			"kind" : "codemodel",
			"version" : 
			{
				"major" : 2,
				"minor" : 7
			}
		}
	}
}
